sendchamp/__init__.py
sendchamp/_http_client.py
sendchamp/constants.py
sendchamp/error.py
sendchamp/sendchamp.py
sendchamp/services/__init__.py
sendchamp/services/customer.py
sendchamp/services/email.py
sendchamp/services/sms.py
sendchamp/services/verification.py
sendchamp/services/voice.py
sendchamp/services/whatsapp.py
sendchamp-0.0.2.dist-info/LICENSE
sendchamp-0.0.2.dist-info/METADATA
sendchamp-0.0.2.dist-info/WHEEL
sendchamp-0.0.2.dist-info/top_level.txt
sendchamp-0.0.2.dist-info/RECORD
