Metadata-Version: 2.1
Name: sendchamp
Version: 0.0.2
Summary: Sendchamp API wrapper
Home-page: https://github.com/Maxzeno/sendchamp
Author: Emmanuel Nwaegunwa
Author-email: Emmanuel Nwaegunwa <emmanuelnwaegunwa@gmail.com>
Project-URL: Homepage, https://github.com/Maxzeno/sendchamp
Project-URL: Issues, https://github.com/Maxzeno/sendchamp/issues
Classifier: Programming Language :: Python :: 3
Classifier: License :: OSI Approved :: MIT License
Classifier: Operating System :: OS Independent
Requires-Python: >=3.8
License-File: LICENSE
